{
  "dwg_path": "C:/Users/nweck/Dropbox/BlueTree/Demo/Projects/2501 - Snowdon Towers/2. Project Inputs/2.1 Drawings/Hydraulic/2025-11-24/P100_PLAN-L0SANITARY.dwg",
  "layer_count": 47,
  "layers": [
    {
      "name": "0",
      "color": 7,
      "linetype": "Continuous",
      "lineweight": -3,
      "locked": false,
      "frozen": false,
      "on": true
    },
    {
      "name": "S-STRS-____-OTLN",
      "color": 31,
      "linetype": "Continuous",
      "lineweight": 9,
      "locked": false,
      "frozen": false,
      "on": true
    },
    {
      "name": "A-FLOR-HRAL-OTLN",
      "color": 11,
      "linetype": "Continuous",
      "lineweight": 9,
      "locked": false,
      "frozen": false,
      "on": true
    },
    {
      "name": "A-WALL-____-OTLN",
      "color": 113,
      "linetype": "Continuous",
      "lineweight": 9,
      "locked": false,
      "frozen": false,
      "on": true
    },
    {
      "name": "A-DOOR-____-OTLN",
      "color": 31,
      "linetype": "Continuous",
      "lineweight": 9,
      "locked": false,
      "frozen": false,
      "on": true
    },
    {
      "name": "A-VRTC-____-OTLN",
      "color": 13,
      "linetype": "Continuous",
      "lineweight": 9,
      "locked": false,
      "frozen": false,
      "on": true
    },
    {
      "name": "Q-SPCQ-____-OTLN",
      "color": 91,
      "linetype": "Continuous",
      "lineweight": 9,
      "locked": false,
      "frozen": false,
      "on": true
    },
    {
      "name": "C-PRKG-____-OTLN",
      "color": 70,
      "linetype": "Continuous",
      "lineweight": 9,
      "locked": false,
      "frozen": false,
      "on": true
    },
    {
      "name": "L-SITE-____-OTLN",
      "color": 91,
      "linetype": "Continuous",
      "lineweight": 9,
      "locked": false,
      "frozen": false,
      "on": true
    },
    {
      "name": "Q-CASE-____-OTLN",
      "color": 31,
      "linetype": "Continuous",
      "lineweight": 9,
      "locked": false,
      "frozen": false,
      "on": true
    },
    {
      "name": "A-COLS-____-OTLN",
      "color": 52,
      "linetype": "Continuous",
      "lineweight": 9,
      "locked": false,
      "frozen": false,
      "on": true
    },
    {
      "name": "A-FLOR-____-OTLN",
      "color": 192,
      "linetype": "Continuous",
      "lineweight": 13,
      "locked": false,
      "frozen": false,
      "on": true
    },
    {
      "name": "C-PROP-LINE-OTLN",
      "color": 91,
      "linetype": "Double Dash 3_8_",
      "lineweight": 20,
      "locked": false,
      "frozen": false,
      "on": true
    },
    {
      "name": "A-GENM-____-OTLN",
      "color": 13,
      "linetype": "Continuous",
      "lineweight": 9,
      "locked": false,
      "frozen": false,
      "on": true
    },
    {
      "name": "E-ELEC-EQPM-OTLN",
      "color": 71,
      "linetype": "Continuous",
      "lineweight": 50,
      "locked": false,
      "frozen": false,
      "on": true
    },
    {
      "name": "E-POWR-CNDT-OTLN",
      "color": 130,
      "linetype": "Continuous",
      "lineweight": 9,
      "locked": false,
      "frozen": false,
      "on": true
    },
    {
      "name": "E-ARBL-BNDY-OTLN",
      "color": 71,
      "linetype": "Continuous",
      "lineweight": 70,
      "locked": false,
      "frozen": false,
      "on": true
    },
    {
      "name": "P-PIPE-____-OTLN",
      "color": 3,
      "linetype": "Continuous",
      "lineweight": 70,
      "locked": false,
      "frozen": false,
      "on": true
    },
    {
      "name": "P-EQPM-OTLN",
      "color": 6,
      "linetype": "Continuous",
      "lineweight": 20,
      "locked": false,
      "frozen": false,
      "on": true
    },
    {
      "name": "E-POWR-DROP-OTLN",
      "color": 130,
      "linetype": "Continuous",
      "lineweight": 13,
      "locked": false,
      "frozen": false,
      "on": true
    },
    {
      "name": "A-WALL-____-PATT",
      "color": 111,
      "linetype": "Continuous",
      "lineweight": 20,
      "locked": false,
      "frozen": false,
      "on": true
    },
    {
      "name": "S-FNDN-____-MCUT",
      "color": 32,
      "linetype": "Continuous",
      "lineweight": 20,
      "locked": false,
      "frozen": false,
      "on": true
    },
    {
      "name": "S-STRS-____-MBND",
      "color": 31,
      "linetype": "Overhead 1_16_",
      "lineweight": 9,
      "locked": false,
      "frozen": false,
      "on": true
    },
    {
      "name": "A-FLOR-HRAL-MBND",
      "color": 11,
      "linetype": "Overhead 1_16_",
      "lineweight": 9,
      "locked": false,
      "frozen": false,
      "on": true
    },
    {
      "name": "A-WALL-____-MCUT",
      "color": 113,
      "linetype": "Continuous",
      "lineweight": 20,
      "locked": false,
      "frozen": false,
      "on": true
    },
    {
      "name": "A-DOOR-FRAM-MCUT",
      "color": 31,
      "linetype": "Continuous",
      "lineweight": 20,
      "locked": false,
      "frozen": false,
      "on": true
    },
    {
      "name": "A-DOOR-____-MCUT",
      "color": 31,
      "linetype": "Continuous",
      "lineweight": 20,
      "locked": false,
      "frozen": false,
      "on": true
    },
    {
      "name": "A-VRTC-____-MCUT",
      "color": 13,
      "linetype": "Continuous",
      "lineweight": 20,
      "locked": false,
      "frozen": false,
      "on": true
    },
    {
      "name": "Q-SPCQ-____-HDLN",
      "color": 91,
      "linetype": "Dash",
      "lineweight": 9,
      "locked": false,
      "frozen": false,
      "on": true
    },
    {
      "name": "I-WALL-____-MCUT",
      "color": 2,
      "linetype": "Continuous",
      "lineweight": 20,
      "locked": false,
      "frozen": false,
      "on": true
    },
    {
      "name": "A-COLS-____-MCUT",
      "color": 52,
      "linetype": "Continuous",
      "lineweight": 30,
      "locked": false,
      "frozen": false,
      "on": true
    },
    {
      "name": "A-DETL-____-MBND",
      "color": 5,
      "linetype": "Continuous",
      "lineweight": 9,
      "locked": false,
      "frozen": false,
      "on": true
    },
    {
      "name": "E-POWR-RISE-OTLN",
      "color": 130,
      "linetype": "Continuous",
      "lineweight": 13,
      "locked": false,
      "frozen": false,
      "on": true
    },
    {
      "name": "S-RBAR-____-MCUT",
      "color": 171,
      "linetype": "Continuous",
      "lineweight": 9,
      "locked": false,
      "frozen": false,
      "on": true
    },
    {
      "name": "A-DETL-____-OTLN",
      "color": 90,
      "linetype": "Hidden 1_16_",
      "lineweight": 9,
      "locked": false,
      "frozen": false,
      "on": true
    },
    {
      "name": "S-GRID-____-OTLN",
      "color": 1,
      "linetype": "Continuous",
      "lineweight": 9,
      "locked": false,
      "frozen": false,
      "on": true
    },
    {
      "name": "S-GRID-____-IDEN",
      "color": 1,
      "linetype": "Continuous",
      "lineweight": 9,
      "locked": false,
      "frozen": false,
      "on": true
    },
    {
      "name": "G-____-____-SYMB",
      "color": 111,
      "linetype": "Continuous",
      "lineweight": 9,
      "locked": false,
      "frozen": false,
      "on": true
    },
    {
      "name": "M-AREA-____-IDEN",
      "color": 171,
      "linetype": "Continuous",
      "lineweight": 9,
      "locked": false,
      "frozen": false,
      "on": true
    },
    {
      "name": "G-____-____-NPLT",
      "color": 191,
      "linetype": "Continuous",
      "lineweight": -3,
      "locked": false,
      "frozen": false,
      "on": true
    },
    {
      "name": "G-____-TTLB-OTLN",
      "color": 6,
      "linetype": "Continuous",
      "lineweight": 9,
      "locked": false,
      "frozen": false,
      "on": true
    },
    {
      "name": "G-____-TTLB-THIN",
      "color": 151,
      "linetype": "Continuous",
      "lineweight": 9,
      "locked": false,
      "frozen": false,
      "on": true
    },
    {
      "name": "G-____-TTLB-MEDM",
      "color": 33,
      "linetype": "Continuous",
      "lineweight": 20,
      "locked": false,
      "frozen": false,
      "on": true
    },
    {
      "name": "A-____-NOTE-TEXT",
      "color": 131,
      "linetype": "Continuous",
      "lineweight": 9,
      "locked": false,
      "frozen": false,
      "on": true
    },
    {
      "name": "G-____-____-SCHD",
      "color": 231,
      "linetype": "Continuous",
      "lineweight": 9,
      "locked": false,
      "frozen": false,
      "on": true
    },
    {
      "name": "A-DETL-____-THIN",
      "color": 151,
      "linetype": "Continuous",
      "lineweight": 9,
      "locked": false,
      "frozen": false,
      "on": true
    },
    {
      "name": "Hyd_Pipe_Water_CW",
      "color": 140,
      "linetype": "HYD_COLD_WATER",
      "lineweight": 50,
      "locked": false,
      "frozen": false,
      "on": true
    }
  ],
  "summary": "47 layers found in drawing."
}